{
  "user": [
    {
      "id": "1",
      "userId": "1",
      "password": "1234",
      "nickname": "여누",
      "hopeExpense": 1000000,
      "plannedMonthlyExpenseByCategory": [
        {
          "category": "식비",
          "amount": 100000
        },
        {
          "category": "교통비",
          "amount": 200000
        },
        {
          "category": "여가비",
          "amount": 300000
        },
        {
          "category": "쇼핑비",
          "amount": 400000
        },
        {
          "category": "생활비",
          "amount": 500000
        },
        {
          "category": "",
          "amount": 0
        }
      ]
    },
    {
      "id": "5744",
      "userId": "",
      "password": "",
      "nickname": "",
      "hopeExpense": 0,
      "plannedMonthlyExpenseByCategory": [
        {
          "category": "식비",
          "amount": 0
        },
        {
          "category": "교통비",
          "amount": 0
        },
        {
          "category": "주거비",
          "amount": 0
        },
        {
          "category": "여가비",
          "amount": 0
        },
        {
          "category": "의료비",
          "amount": 0
        },
        {
          "category": "문화비",
          "amount": 0
        },
        {
          "category": "교육비",
          "amount": 0
        },
        {
          "category": "기타",
          "amount": 0
        }
      ]
    },
    {
      "id": "25ce",
      "userId": "1234",
      "password": "1234",
      "nickname": "하히아",
      "hopeExpense": 0,
      "plannedMonthlyExpenseByCategory": [
        {
          "category": "식비",
          "amount": 0
        },
        {
          "category": "교통비",
          "amount": 0
        },
        {
          "category": "주거비",
          "amount": 0
        },
        {
          "category": "여가비",
          "amount": 0
        },
        {
          "category": "의료비",
          "amount": 0
        },
        {
          "category": "문화비",
          "amount": 0
        },
        {
          "category": "교육비",
          "amount": 0
        },
        {
          "category": "기타",
          "amount": 0
        }
      ]
    },
    {
      "id": "15f6",
      "userId": "12",
      "password": "1234",
      "nickname": "123",
      "hopeExpense": 0,
      "plannedMonthlyExpenseByCategory": [
        {
          "category": "식비",
          "amount": 0
        },
        {
          "category": "교통비",
          "amount": 0
        },
        {
          "category": "주거비",
          "amount": 0
        },
        {
          "category": "여가비",
          "amount": 0
        },
        {
          "category": "의료비",
          "amount": 0
        },
        {
          "category": "문화비",
          "amount": 0
        },
        {
          "category": "교육비",
          "amount": 0
        },
        {
          "category": "기타",
          "amount": 0
        }
      ]
    }
  ],
  "history": [],
  "monthlyExpense": [],
  "dailyExpense": []
}
